LICENSE
README.md
setup.py
tools/weipyweb-path-deploy
weipyweb/__init__.py
weipyweb/__version__.py
weipyweb/exceptions.py
weipyweb/input.py
weipyweb/io_ctrl.py
weipyweb/output.py
weipyweb/pin.py
weipyweb/utils.py
weipyweb.egg-info/PKG-INFO
weipyweb.egg-info/SOURCES.txt
weipyweb.egg-info/dependency_links.txt
weipyweb.egg-info/requires.txt
weipyweb.egg-info/top_level.txt
weipyweb/html/codemirror/active-line.js
weipyweb/html/codemirror/addons.js
weipyweb/html/codemirror/autorefresh.js
weipyweb/html/codemirror/loadmode.js
weipyweb/html/codemirror/matchbrackets.js
weipyweb/html/codemirror/python.js
weipyweb/html/css/app.css
weipyweb/html/css/bootstrap-select.min.css
weipyweb/html/css/codemirror.min.css
weipyweb/html/css/markdown.min.css
weipyweb/html/css/toastify.min.css
weipyweb/html/css/bs-theme/dark.min.css
weipyweb/html/css/bs-theme/default.min.css
weipyweb/html/css/bs-theme/minty.min.css
weipyweb/html/css/bs-theme/sketchy.min.css
weipyweb/html/css/bs-theme/yeti.min.css
weipyweb/html/image/favicon_closed_32.png
weipyweb/html/image/favicon_open_16.png
weipyweb/html/js/FileSaver.min.js
weipyweb/html/js/bootstrap-select.min.js
weipyweb/html/js/bootstrap.min.js
weipyweb/html/js/bs-custom-file-input.min.js
weipyweb/html/js/codemirror.min.js
weipyweb/html/js/jquery.min.js
weipyweb/html/js/mustache.min.js
weipyweb/html/js/popper.min.js
weipyweb/html/js/prism.min.js
weipyweb/html/js/purify.min.js
weipyweb/html/js/require.min.js
weipyweb/html/js/toastify.min.js
weipyweb/html/js/weipyweb.min.js
weipyweb/platform/__init__.py
weipyweb/platform/aiohttp.py
weipyweb/platform/bokeh.py
weipyweb/platform/django.py
weipyweb/platform/fastapi.py
weipyweb/platform/flask.py
weipyweb/platform/httpbased.py
weipyweb/platform/page.py
weipyweb/platform/path_deploy.py
weipyweb/platform/remote_access.py
weipyweb/platform/tornado.py
weipyweb/platform/tornado_http.py
weipyweb/platform/utils.py
weipyweb/platform/tpl/index.html
weipyweb/session/__init__.py
weipyweb/session/base.py
weipyweb/session/coroutinebased.py
weipyweb/session/threadbased.py