Metadata-Version: 2.1
Name: weipyweb
Version: 0.0.2
Summary: Beautify the original weipyweb
Home-page: https://github.com/acloudtwei
Author: Acloudtwei
Author-email: 1559295172@qq.com
License: MIT
Project-URL: Documentation, https://pywebio.readthedocs.io
Platform: UNKNOWN
Classifier: Programming Language :: Python :: 3
Classifier: Programming Language :: Python :: 3.5
Classifier: Programming Language :: Python :: 3.6
Classifier: Programming Language :: Python :: 3.7
Classifier: Programming Language :: Python :: 3.8
Requires-Python: >=3.5.2
Provides-Extra: flask
Provides-Extra: django
Provides-Extra: aiohttp
Provides-Extra: bokeh
Provides-Extra: doc
Provides-Extra: all
License-File: LICENSE
